{
    "main": 
    {
        "11": "a",
        "b1": "b",
        "wd": "c",
        "g6": "d",
        "e6": "e",
        "nm": "f",
        "nj": "g",
        "g9": "h",
        "go": "i",
        "92": "j",
        "79": "k",
        "1e": "l",
        "sd": "m",
        "1d": "n",
        "7e": "o",
        "dh": "p",
        "36": "q",
        "bn": "r",
        "l9": "s",
        "f5": "t",
        "gf": "u",
        "f9": "v",
        "7h": "w",
        "fe": "x",
        "ji": "y",
        "93": "z",
        "vh": "!",
        "md": "'",
        "6h": "£",
        "9j": "$",
        "sw": "%",
        "s7": "^",
        "tz": "&",
        "zy": "*",
        "8z": "(",
        "lp": ")",
        "g3": "-",
        "mn": "_",
        "39": "=",
        "12": "+",
        "xp": ",",
        "gy": "<",
        "q3": ">",
        "b9": ".",
        "d4": "/",
        "d5": "?",
        "8s": "[",
        "cb": "]",
        "8g": ";",
        "kj": "@",
        "45": ":",
        "27": "{",
        "ht": "1",
        "94": "2",
        "fb": "3",
        "h5": "4",
        "4k": "5",
        "j5": "6",
        "57": "7",
        "72": "8",
        "14": "9",
        "4h": "0",
        "w8": "#",
        "w5": "`",
        "k8": "¬",
        "bh": "~"
    },

    "num":
    {
        "10": "a",
        "11": "b",
        "12": "c",
        "13": "d",
        "14": "e",
        "15": "f",
        "16": "g",
        "17": "h",
        "18": "i",
        "19": "j",
        "20": "k",
        "21": "l",
        "22": "m",
        "23": "n",
        "24": "o",
        "25": "p",
        "26": "q",
        "27": "r",
        "28": "s",
        "29": "t",
        "30": "u",
        "31": "v",
        "32": "w",
        "33": "x",
        "34": "y",
        "35": "z",
        "36": "!",
        "37": "'",
        "38": "£",
        "39": "$",
        "40": "%",
        "41": "^",
        "42": "&",
        "43": "*",
        "44": "(",
        "45": ")",
        "46": "-",
        "47": "_",
        "48": "=",
        "49": "+",
        "50": ",",
        "51": "<",
        "52": ">",
        "53": ".",
        "54": "/",
        "55": "?",
        "56": "[",
        "57": "]",
        "58": ";",
        "59": "@",
        "60": ":",
        "61": "{",
        "62": "1",
        "63": "2",
        "64": "3",
        "65": "4",
        "66": "5",
        "67": "6",
        "68": "7",
        "69": "8",
        "70": "9",
        "71": "0",
        "72": "#",
        "73": "`",
        "74": "¬",
        "75": "~"
    }
}
